llama_stack_provider_lmeval/__init__.py
llama_stack_provider_lmeval/compat.py
llama_stack_provider_lmeval/config.py
llama_stack_provider_lmeval/errors.py
llama_stack_provider_lmeval/lmeval.py
llama_stack_provider_lmeval/provider.py
llama_stack_provider_lmeval-0.4.2.dist-info/licenses/LICENSE
llama_stack_provider_lmeval-0.4.2.dist-info/METADATA
llama_stack_provider_lmeval-0.4.2.dist-info/WHEEL
llama_stack_provider_lmeval-0.4.2.dist-info/top_level.txt
llama_stack_provider_lmeval-0.4.2.dist-info/RECORD
