Metadata-Version: 2.4
Name: llama-stack-provider-lmeval
Version: 0.4.2
Summary: Add your description here
Requires-Python: >=3.12
License-File: LICENSE
Requires-Dist: llama-stack
Requires-Dist: kubernetes==35.0.0a1
Requires-Dist: fastapi
Requires-Dist: opentelemetry-api
Requires-Dist: opentelemetry-exporter-otlp
Requires-Dist: aiosqlite
Requires-Dist: uvicorn
Requires-Dist: ipykernel
Provides-Extra: dev
Requires-Dist: pytest; extra == "dev"
Requires-Dist: pytest-cov; extra == "dev"
Requires-Dist: black; extra == "dev"
Requires-Dist: isort; extra == "dev"
Requires-Dist: ruff; extra == "dev"
Requires-Dist: llama-stack==0.3.5; extra == "dev"
Dynamic: license-file
